fisi/__init__.py
fisi/assets.py
fisi/base.py
fisi/constants.py
fisi/events.py
fisi/flows.py
fisi/growth.py
fisi/model.py
fisi/taxes.py
fisi/data/historic_annual_growth_rates.csv
fisi-0.1.1.dist-info/LICENSE
fisi-0.1.1.dist-info/METADATA
fisi-0.1.1.dist-info/WHEEL
fisi-0.1.1.dist-info/top_level.txt
fisi-0.1.1.dist-info/RECORD
