Metadata-Version: 2.1
Name: fisi
Version: 0.1.1
Summary: Simulate personal finances over time
Author: pquinter
Project-URL: Homepage, https://github.com/pquinter/fisim
Classifier: Programming Language :: Python :: 3
Classifier: License :: OSI Approved :: MIT License
Classifier: Operating System :: OS Independent
Requires-Python: >=3.7
License-File: LICENSE
Requires-Dist: numpy
Requires-Dist: matplotlib
Requires-Dist: pandas
Provides-Extra: dev
Requires-Dist: pytest ; extra == 'dev'
Requires-Dist: ruff ; extra == 'dev'
Requires-Dist: pre-commit ; extra == 'dev'
